trame/__init__.py
trame/modules/__init__.py
trame/modules/www.py
trame/ui/__init__.py
trame/ui/html.py
trame/widgets/__init__.py
trame/widgets/client.py
trame/widgets/html.py
trame_client/LICENSE
trame_client/__init__.py
trame_client/encoders/__init__.py
trame_client/encoders/numpy.py
trame_client/module/__init__.py
trame_client/module/vue2.py
trame_client/module/vue3.py
trame_client/module/vue2-www/index.html
trame_client/module/vue2-www/loading.tpl
trame_client/module/vue2-www/logo.png
trame_client/module/vue2-www/vue.global.js
trame_client/module/vue2-www/css/app.0b077e70.css
trame_client/module/vue2-www/js/app.7d0e64a7.js
trame_client/module/vue2-www/js/chunk-vendors.3aa0189c.js
trame_client/module/vue3-www/index.html
trame_client/module/vue3-www/loading.tpl
trame_client/module/vue3-www/logo.png
trame_client/module/vue3-www/vue.global.js
trame_client/resources/attributes.json
trame_client/resources/events.json
trame_client/resources/vue.json
trame_client/ui/__init__.py
trame_client/ui/core.py
trame_client/ui/html.py
trame_client/utils/__init__.py
trame_client/utils/defaults.py
trame_client/utils/formatter.py
trame_client/utils/jupyter.py
trame_client/utils/testing.py
trame_client/utils/version.py
trame_client/utils/web_module.py
trame_client/widgets/__init__.py
trame_client/widgets/core.py
trame_client/widgets/generator.py
trame_client/widgets/html.py
trame_client/widgets/trame.py
trame_client_lichen-3.1.1.dist-info/LICENSE
trame_client_lichen-3.1.1.dist-info/METADATA
trame_client_lichen-3.1.1.dist-info/WHEEL
trame_client_lichen-3.1.1.dist-info/top_level.txt
trame_client_lichen-3.1.1.dist-info/RECORD
