Metadata-Version: 2.1
Name: trame-client-lichen
Version: 3.1.1
Summary: Internal client of trame
Author: Lichen Commodities
License: MIT
Keywords: Python,Interactive,Web,Application,Framework
Classifier: Development Status :: 5 - Production/Stable
Classifier: Environment :: Web Environment
Classifier: License :: OSI Approved :: MIT License
Classifier: Natural Language :: English
Classifier: Operating System :: OS Independent
Classifier: Programming Language :: Python :: 3 :: Only
Classifier: Programming Language :: JavaScript
Classifier: Topic :: Software Development :: Libraries :: Application Frameworks
Classifier: Topic :: Software Development :: Libraries :: Python Modules
License-File: LICENSE
Provides-Extra: test
Requires-Dist: pytest ; extra == 'test'
Requires-Dist: seleniumbase ; extra == 'test'
Requires-Dist: pytest-xprocess ; extra == 'test'
Requires-Dist: Pillow ; extra == 'test'
Requires-Dist: pixelmatch ; extra == 'test'
